Cargo.lock
Cargo.toml
LICENSE
MANIFEST.in
README.md
pyproject.toml
setup.py
bin/pyawabi
pyawabi/__init__.py
pyawabi.egg-info/PKG-INFO
pyawabi.egg-info/SOURCES.txt
pyawabi.egg-info/dependency_links.txt
pyawabi.egg-info/not-zip-safe
pyawabi.egg-info/top_level.txt
tests/test_tokenizer.py