Metadata-Version: 2.4
Name: pyawabi
Version: 0.3.1
Summary: A python wrapper for awabi
Home-page: http://github.com/nakagami/pyawabi/
Author: Hajime Nakagami
Author-email: Hajime Nakagami <nakagami@gmail.com>
License: MIT License
Project-URL: Homepage, https://github.com/nakagami/pyawabi
Keywords: mecab,awabi
Classifier: Development Status :: 4 - Beta
Classifier: Intended Audience :: Developers
Classifier: License :: OSI Approved :: MIT License
Classifier: Programming Language :: Python
Classifier: Programming Language :: Python :: 3
Classifier: Programming Language :: Rust
Classifier: Operating System :: POSIX
License-File: LICENSE
Dynamic: author
Dynamic: home-page
Dynamic: license-file
